minisampy/__init__.py
minisampy/_minisam_py_wrapper.cpython-37m-x86_64-linux-gnu.so
minisampy/libminisam.so
minisampy/sophus/__init__.py
minisampy/sophus/_minisam_sophus_py_wrapper.cpython-37m-x86_64-linux-gnu.so
minisampy-0.0.9.dist-info/LICENSE
minisampy-0.0.9.dist-info/METADATA
minisampy-0.0.9.dist-info/WHEEL
minisampy-0.0.9.dist-info/top_level.txt
minisampy-0.0.9.dist-info/RECORD
